[
    { "title": "Inception", "genre": "Sci-Fi" },
    { "title": "Titanic", "genre": "Romance" },
    { "title": "Avatar", "genre": "Sci-Fi" },
    { "title": "Interstellar", "genre": "Sci-Fi" },
    { "title": "Joker", "genre": "Drama" },
    { "title": "The Matrix", "genre": "Sci-Fi" },
    { "title": "Gladiator", "genre": "Action" },
    { "title": "The Godfather", "genre": "Crime" },
    { "title": "Pulp Fiction", "genre": "Crime" },
    { "title": "The Dark Knight", "genre": "Action" },
    { "title": "Fight Club", "genre": "Drama" },
    { "title": "Forrest Gump", "genre": "Drama" },
    { "title": "The Shawshank Redemption", "genre": "Drama" },
    { "title": "Goodfellas", "genre": "Crime" },
    { "title": "The Lord of the Rings: The Fellowship of the Ring", "genre": "Fantasy" },
    { "title": "The Lord of the Rings: The Two Towers", "genre": "Fantasy" },
    { "title": "The Lord of the Rings: The Return of the King", "genre": "Fantasy" },
    { "title": "The Lion King", "genre": "Animation" },
    { "title": "Schindler's List", "genre": "Drama" },
    { "title": "The Silence of the Lambs", "genre": "Thriller" },
    { "title": "Se7en", "genre": "Thriller" },
    { "title": "Avengers: Endgame", "genre": "Action" },
    { "title": "Avengers: Infinity War", "genre": "Action" },
    { "title": "The Avengers", "genre": "Action" },
    { "title": "Black Panther", "genre": "Action" },
    { "title": "Iron Man", "genre": "Action" },
    { "title": "Captain America: The Winter Soldier", "genre": "Action" },
    { "title": "Spider-Man: No Way Home", "genre": "Action" },
    { "title": "Star Wars: A New Hope", "genre": "Sci-Fi" },
    { "title": "Star Wars: The Empire Strikes Back", "genre": "Sci-Fi" },
    { "title": "Star Wars: Return of the Jedi", "genre": "Sci-Fi" },
    { "title": "Django Unchained", "genre": "Western" },
    { "title": "The Hateful Eight", "genre": "Western" },
    { "title": "Once Upon a Time in Hollywood", "genre": "Drama" },
    { "title": "Kill Bill: Vol. 1", "genre": "Action" },
    { "title": "Kill Bill: Vol. 2", "genre": "Action" },
    { "title": "The Departed", "genre": "Crime" },
    { "title": "The Revenant", "genre": "Drama" },
    { "title": "Mad Max: Fury Road", "genre": "Action" },
    { "title": "The Grand Budapest Hotel", "genre": "Comedy" }
  ]
  